{
    "code": [
        {
            "cpp": [
                {
                    "file": 0,
                    "lines": 0,
                    "note": 0,
                    "null": 0
                }
            ],
            "c": [
                {
                    "file": 0,
                    "lines": 0,
                    "note": 0,
                    "null": 0
                }
            ],
            "php": [
                {
                    "file": 0,
                    "lines": 0,
                    "note": 0,
                    "null": 0
                }
            ],
            "py": [
                {
                    "file": 0,
                    "lines": 0,
                    "note": 0,
                    "null": 0
                }
            ],
            "go": [
                {
                    "file": 0,
                    "lines": 0,
                    "note": 0,
                    "null": 0
                }
            ],
            "js": [
                {
                    "file": 0,
                    "lines": 0,
                    "note": 0,
                    "null": 0
                }
            ],
            "sh": [
                {
                    "file": 0,
                    "lines": 0,
                    "note": 0,
                    "null": 0
                }
            ],
            "java": [
                {
                    "file": 0,
                    "lines": 0,
                    "note": 0,
                    "null": 0
                }
            ],
            "html": [
                {
                    "file": 0,
                    "lines": 0,
                    "note": 0,
                    "null": 0
                }
            ]
        }
    ],
    "data": [
        {
            "data-y": [
                {
                    "file": 0,
                    "type": "cpp",
                    "lines": 0
                },
                {
                    "file": 0,
                    "type": "c",
                    "lines": 0
                },
                {
                    "file": 0,
                    "type": "php",
                    "lines": 0
                },
                {
                    "file": 0,
                    "type": "js",
                    "lines": 0
                },
                {
                    "file": 0,
                    "type": "py",
                    "lines": 0
                },
                {
                    "file": 0,
                    "type": "sh",
                    "lines": 0
                },
                {
                    "file": 0,
                    "type": "html",
                    "lines": 0
                },
                {
                    "file": 0,
                    "type": "go",
                    "lines": 0
                },
                {
                    "file": 0,
                    "type": "java",
                    "lines": 0
                }
            ],
            "data-m": [
                {
                    "file": 0,
                    "type": "cpp",
                    "lines": 0
                },
                {
                    "file": 0,
                    "type": "c",
                    "lines": 0
                },
                {
                    "file": 0,
                    "type": "php",
                    "lines": 0
                },
                {
                    "file": 0,
                    "type": "js",
                    "lines": 0
                },
                {
                    "file": 0,
                    "type": "py",
                    "lines": 0
                },
                {
                    "file": 0,
                    "type": "sh",
                    "lines": 0
                },
                {
                    "file": 0,
                    "type": "html",
                    "lines": 0
                },
                {
                    "file": 0,
                    "type": "go",
                    "lines": 0
                },
                {
                    "file": 0,
                    "type": "java",
                    "lines": 0
                }
            ],
            "data-w": [
                {
                    "file": 0,
                    "type": "cpp",
                    "lines": 0
                },
                {
                    "file": 0,
                    "type": "c",
                    "lines": 0
                },
                {
                    "file": 0,
                    "type": "php",
                    "lines": 0
                },
                {
                    "file": 0,
                    "type": "js",
                    "lines": 0
                },
                {
                    "file": 0,
                    "type": "py",
                    "lines": 0
                },
                {
                    "file": 0,
                    "type": "sh",
                    "lines": 0
                },
                {
                    "file": 0,
                    "type": "html",
                    "lines": 0
                },
                {
                    "file": 0,
                    "type": "go",
                    "lines": 0
                },
                {
                    "file": 0,
                    "type": "java",
                    "lines": 0
                }
            ],
            "data-d": [
                {
                    "file": 0,
                    "type": "cpp",
                    "lines": 0
                },
                {
                    "file": 0,
                    "type": "c",
                    "lines": 0
                },
                {
                    "file": 0,
                    "type": "php",
                    "lines": 0
                },
                {
                    "file": 0,
                    "type": "js",
                    "lines": 0
                },
                {
                    "file": 0,
                    "type": "py",
                    "lines": 0
                },
                {
                    "file": 0,
                    "type": "sh",
                    "lines": 0
                },
                {
                    "file": 0,
                    "type": "html",
                    "lines": 0
                },
                {
                    "file": 0,
                    "type": "go",
                    "lines": 0
                },
                {
                    "file": 0,
                    "type": "java",
                    "lines": 0
                }
            ]
        }
    ]
}